_libsemigroups_pybind11.cpython-314-aarch64-linux-musl.so
libsemigroups_pybind11/__init__.py
libsemigroups_pybind11/_version.py
libsemigroups_pybind11/action.py
libsemigroups_pybind11/adapters.py
libsemigroups_pybind11/aho_corasick.py
libsemigroups_pybind11/bipartition.py
libsemigroups_pybind11/blocks.py
libsemigroups_pybind11/bmat8.py
libsemigroups_pybind11/congruence.py
libsemigroups_pybind11/forest.py
libsemigroups_pybind11/froidure_pin.py
libsemigroups_pybind11/hpcombi.py
libsemigroups_pybind11/is_obviously_infinite.py
libsemigroups_pybind11/kambites.py
libsemigroups_pybind11/knuth_bendix.py
libsemigroups_pybind11/konieczny.py
libsemigroups_pybind11/matrix.py
libsemigroups_pybind11/paths.py
libsemigroups_pybind11/pbr.py
libsemigroups_pybind11/schreier_sims.py
libsemigroups_pybind11/sims.py
libsemigroups_pybind11/stephen.py
libsemigroups_pybind11/to.py
libsemigroups_pybind11/todd_coxeter.py
libsemigroups_pybind11/transf.py
libsemigroups_pybind11/ukkonen.py
libsemigroups_pybind11/word_graph.py
libsemigroups_pybind11/words.py
libsemigroups_pybind11/detail/__init__.py
libsemigroups_pybind11/detail/congruence_common.py
libsemigroups_pybind11/detail/cxx_wrapper.py
libsemigroups_pybind11/detail/decorators.py
libsemigroups_pybind11/detail/dot.py
libsemigroups_pybind11/detail/tools.py
libsemigroups_pybind11/presentation/__init__.py
libsemigroups_pybind11/presentation/examples.py
libsemigroups_pybind11.libs/libgcc_s-2d945d6c.so.1
libsemigroups_pybind11.libs/libsemigroups-b46ef204.so.3.0.0
libsemigroups_pybind11.libs/libstdc++-85f2cd6d.so.6.0.33
libsemigroups_pybind11-1.3.0.dist-info/METADATA
libsemigroups_pybind11-1.3.0.dist-info/WHEEL
libsemigroups_pybind11-1.3.0.dist-info/top_level.txt
libsemigroups_pybind11-1.3.0.dist-info/RECORD
libsemigroups_pybind11-1.3.0.dist-info/licenses/LICENSE
libsemigroups_pybind11-1.3.0.dist-info/sboms/auditwheel.cdx.json
