Metadata-Version: 2.4
Name: libsemigroups_pybind11
Version: 1.3.0
Summary: A python package for the libsemigroups C++ library.
Author-email: Reinis Cirpons <rc234@st-andrews.ac.uk>, Joseph Edwards <jde1@st-andrews.ac.uk>, James Mitchell <jdm3@st-andrews.ac.uk>, Maria Tsalakou <mt200@st-andrews.ac.uk>, Murray Whyte <mw231@st-andrews.ac.uk>
License-Expression: GPL-3.0-or-later
Project-URL: Changelog, https://libsemigroups.github.io/libsemigroups_pybind11/changelog.html
Project-URL: Documentation, https://libsemigroups.github.io/libsemigroups_pybind11/
Project-URL: Homepage, https://github.com/libsemigroups/libsemigroups_pybind11
Project-URL: Issues, https://github.com/libsemigroups/libsemigroups_pybind11/issues
Classifier: Development Status :: 5 - Production/Stable
Classifier: Programming Language :: Python :: 3 :: Only
Classifier: Programming Language :: Python :: 3.9
Classifier: Programming Language :: Python :: 3.10
Classifier: Programming Language :: Python :: 3.11
Classifier: Programming Language :: Python :: 3.12
Classifier: Programming Language :: Python :: 3.13
Classifier: Programming Language :: Python :: 3.14
Classifier: Intended Audience :: Science/Research
Classifier: Topic :: Scientific/Engineering :: Mathematics
Classifier: Natural Language :: English
Requires-Python: >=3.10
License-File: LICENSE
Requires-Dist: graphviz>=0.21
Requires-Dist: numpy>=2.2.6
Requires-Dist: typing-extensions>=4.15.0
Provides-Extra: docs
Requires-Dist: beautifulsoup4>=4.14.2; extra == "docs"
Requires-Dist: sphinx>=8.2; python_full_version >= "3.11" and extra == "docs"
Requires-Dist: sphinx>=8.1.3; python_full_version < "3.11" and extra == "docs"
Requires-Dist: sphinx-copybutton>=0.5.2; extra == "docs"
Requires-Dist: sphinx-rtd-theme>=3.0.2; extra == "docs"
Requires-Dist: sphinxcontrib-bibtex>=2.6.5; extra == "docs"
Provides-Extra: test
Requires-Dist: pytest>=8.4.2; extra == "test"
Dynamic: license-file
